{
  "app_id": "34491023653875075",
  "package_name": "com.Project.ye",
  "id_source": "known",
  "status": "ok",
  "status_message": null,
  "name": "Project ye",
  "rating_average": 3.9285714285714,
  "rating_count": 14,
  "review_count": 7,
  "reviews": [
    {
      "id": "1093050510552425",
      "score": 5,
      "review_title": "Www game",
      "review_description": "This game is so fun me and friends play it so much and we have a great time",
      "date": 1774568724,
      "review_helpful_count": 3,
      "author_display_name": "pho3nix2k",
      "author_alias": "pho3nix2k",
      "developer_response": null
    },
    {
      "id": "1047636265102641",
      "score": 5,
      "review_title": "I aplyed for mod im m1 jr on dc",
      "review_description": "Hiii",
      "date": 1774582885,
      "review_helpful_count": 2,
      "author_display_name": "mouse.da.femboy",
      "author_alias": "mouse.da.femboy",
      "developer_response": null
    },
    {
      "id": "961949823677893",
      "score": 1,
      "review_title": "Disappointment",
      "review_description": "Absolute dog crap of a game, absolutely horrible, do not download.",
      "date": 1774298024,
      "review_helpful_count": 0,
      "author_display_name": "MrWaterBottle13",
      "author_alias": "MrWaterBottle13",
      "developer_response": null
    },
    {
      "id": "1059254860602478",
      "score": 1,
      "review_title": "Not so good",
      "review_description": "It could be better",
      "date": 1774121916,
      "review_helpful_count": 0,
      "author_display_name": "nooodle._vr",
      "author_alias": "nooodle._vr",
      "developer_response": null
    },
    {
      "id": "1084292944760393",
      "score": 1,
      "review_title": "This game sucks",
      "review_description": "Do not download",
      "date": 1774129593,
      "review_helpful_count": 0,
      "author_display_name": "REDFOX888",
      "author_alias": "REDFOX888",
      "developer_response": null
    },
    {
      "id": "967611729032918",
      "score": 5,
      "review_title": "Bad",
      "review_description": "No",
      "date": 1774214372,
      "review_helpful_count": 1,
      "author_display_name": "CJKcoops",
      "author_alias": "CJKcoops",
      "developer_response": null
    },
    {
      "id": "970722792802282",
      "score": 5,
      "review_title": "Yes",
      "review_description": "WW7W is a smelly boy",
      "date": 1774220302,
      "review_helpful_count": 0,
      "author_display_name": "Deathgoose2012",
      "author_alias": "Deathgoose2012",
      "developer_response": null
    }
  ],
  "total": 7,
  "sort": "helpful",
  "ordering": [
    "TOP"
  ],
  "pages_fetched": 1,
  "fetched_at": "2026-06-19T14:29:50Z"
}