{
  "app_id": "7967440266714594",
  "package_name": "com.VRTech.ParaglideXtreme",
  "id_source": "known",
  "status": "ok",
  "status_message": null,
  "name": "Paraglide Xtreme",
  "rating_average": 1,
  "rating_count": 2,
  "review_count": 2,
  "reviews": [
    {
      "id": "975523958967660",
      "score": 1,
      "review_title": "Awful",
      "review_description": "Game is terrible not worth the time or money.",
      "date": 1768061323,
      "review_helpful_count": 0,
      "author_display_name": "Cloudsurfer45",
      "author_alias": "Cloudsurfer45",
      "developer_response": null
    },
    {
      "id": "1189233686342385",
      "score": 1,
      "review_title": "No buy",
      "review_description": "This game just do almost nothing,\nOnly jump from helicopter.\nGlide has only visual reaction on hands move.\nGarbage...",
      "date": 1757544388,
      "review_helpful_count": 0,
      "author_display_name": "msedlin",
      "author_alias": "msedlin",
      "developer_response": null
    }
  ],
  "total": 2,
  "sort": "helpful",
  "ordering": [
    "TOP"
  ],
  "pages_fetched": 1,
  "fetched_at": "2026-06-19T18:28:19Z"
}