{
  "app_id": "7356262181129327",
  "package_name": "com.AlbinoStudios.AlbinoHorrorVRRemastered",
  "id_source": "known",
  "status": "ok",
  "status_message": null,
  "name": "Albino Horror VR: Remastered",
  "rating_average": 3.2142857142857,
  "rating_count": 28,
  "review_count": 7,
  "reviews": [
    {
      "id": "1783214645661093",
      "score": 5,
      "review_title": "I’m friends with the owner",
      "review_description": "This game is amazing",
      "date": 1762107485,
      "review_helpful_count": 1,
      "author_display_name": "imfocus",
      "author_alias": "imfocus",
      "developer_response": null
    },
    {
      "id": "786922871180718",
      "score": 5,
      "review_title": "Ben you know who it is",
      "review_description": "AWESOMEEEEEEEEEEEWWEEWEEE",
      "date": 1762064664,
      "review_helpful_count": 1,
      "author_display_name": "mr.pyroraptor",
      "author_alias": "mr.pyroraptor",
      "developer_response": null
    },
    {
      "id": "650336070899601",
      "score": 5,
      "review_title": "Art request",
      "review_description": "Hey I really like your game and I’m wondering if you can tell me where I can submit fan art and or make it into a thumbnail for the game I’ve been doing art for 10 years now and I have lots of experience I can share some sample drawing for this game to prove",
      "date": 1740001759,
      "review_helpful_count": 4,
      "author_display_name": "SwagTivity",
      "author_alias": "SwagTivity",
      "developer_response": null
    },
    {
      "id": "596901016213930",
      "score": 2,
      "review_title": "Pretty good",
      "review_description": "The concept of the game was pretty good, but it was a little laggy and was very buggy￼",
      "date": 1734488848,
      "review_helpful_count": 4,
      "author_display_name": "soulzsvr67",
      "author_alias": "soulzsvr67",
      "developer_response": null
    },
    {
      "id": "563786563255026",
      "score": 5,
      "review_title": "Really fun",
      "review_description": "I really like the game. The horror maps are really good 10 out of 10 to the people who made the game. ￼",
      "date": 1732564163,
      "review_helpful_count": 5,
      "author_display_name": "OD.Deadshot",
      "author_alias": "OD.Deadshot",
      "developer_response": {
        "body": "Thank You! :)",
        "date": 1732921289
      }
    },
    {
      "id": "1134279304305930",
      "score": 5,
      "review_title": "Pretty good game",
      "review_description": "This game is pretty fun! Plz play it sometime!",
      "date": 1721455777,
      "review_helpful_count": 7,
      "author_display_name": "ApplebeesManager12",
      "author_alias": "ApplebeesManager12",
      "developer_response": null
    },
    {
      "id": "445820054734589",
      "score": 5,
      "review_title": "VERY GOOD",
      "review_description": "This is very fanum tax",
      "date": 1716909213,
      "review_helpful_count": 13,
      "author_display_name": "Mikoo190",
      "author_alias": "Mikoo190",
      "developer_response": {
        "body": "thank u skibidi sigma",
        "date": 1717531934
      }
    }
  ],
  "total": 7,
  "sort": "helpful",
  "ordering": [
    "TOP"
  ],
  "pages_fetched": 1,
  "fetched_at": "2026-06-19T05:55:57Z"
}