{
  "app_id": "9280943221988610",
  "package_name": "com.TIOSDigital.RopeMan",
  "id_source": "known",
  "status": "ok",
  "status_message": null,
  "name": "RopeMan",
  "rating_average": 3.1,
  "rating_count": 10,
  "review_count": 1,
  "reviews": [
    {
      "id": "851694721370925",
      "score": 4,
      "review_title": "What this game needs",
      "review_description": "Honestly the combat lacks and needs new textures now and maybe some more abilites",
      "date": 1766973656,
      "review_helpful_count": 5,
      "author_display_name": "gdoge27",
      "author_alias": "gdoge27",
      "developer_response": null
    }
  ],
  "total": 1,
  "sort": "helpful",
  "ordering": [
    "TOP"
  ],
  "pages_fetched": 1,
  "fetched_at": "2026-06-19T17:35:16Z"
}