{
  "app_id": "7394670223942605",
  "package_name": "com.FunnyRunnersCompany.FunnyRunners",
  "id_source": "known",
  "status": "ok",
  "status_message": null,
  "name": "Funny Runners",
  "rating_average": 4.6,
  "rating_count": 5,
  "review_count": 3,
  "reviews": [
    {
      "id": "501524986115089",
      "score": 3,
      "review_title": "Can i mod?",
      "review_description": "gg dude. Sigma",
      "date": 1726685954,
      "review_helpful_count": 0,
      "author_display_name": "domce.2024",
      "author_alias": "domce.2024",
      "developer_response": null
    },
    {
      "id": "412406391956034",
      "score": 5,
      "review_title": "Im a mod",
      "review_description": "this owner of this game is so nice\nand the staff are kind \nsuper underrated for only 7 people to play the game while on applab",
      "date": 1725500163,
      "review_helpful_count": 3,
      "author_display_name": "Frzreel",
      "author_alias": "Frzreel",
      "developer_response": null
    },
    {
      "id": "300192543177286",
      "score": 5,
      "review_title": "I very much like it",
      "review_description": "I'm in your discord and I'll get beta tester or test role \non Discord",
      "date": 1714492690,
      "review_helpful_count": 6,
      "author_display_name": "gorillavr48",
      "author_alias": "gorillavr48",
      "developer_response": null
    }
  ],
  "total": 3,
  "sort": "helpful",
  "ordering": [
    "TOP"
  ],
  "pages_fetched": 1,
  "fetched_at": "2026-06-19T10:10:47Z"
}